{"pid": 1, "kind": "hermes-gateway", "argv": ["/opt/hermes/.venv/bin/hermes", "gateway", "run"], "start_time": 39913666, "gateway_state": "running", "exit_reason": null, "restart_requested": false, "active_agents": 0, "platforms": {"feishu": {"state": "connected", "error_code": null, "error_message": null, "updated_at": "2026-06-05T11:53:23.618303+00:00"}, "webhook": {"state": "connected", "error_code": null, "error_message": null, "updated_at": "2026-06-05T11:53:23.675650+00:00"}}, "updated_at": "2026-06-05T11:53:23.680796+00:00"}